pyqtkeybind/__init__.py
pyqtkeybind/win/__init__.py
pyqtkeybind/win/keybindutil.py
pyqtkeybind/win/keycodes.py
pyqtkeybind/x11/__init__.py
pyqtkeybind/x11/keybindutil.py
pyqtkeybind/x11/keysymdef.py
pyqtkeybind/x11/qt_keycodes.py
pyqtkeybind-0.0.9.dist-info/LICENSE.md
pyqtkeybind-0.0.9.dist-info/METADATA
pyqtkeybind-0.0.9.dist-info/WHEEL
pyqtkeybind-0.0.9.dist-info/top_level.txt
pyqtkeybind-0.0.9.dist-info/RECORD
