Metadata-Version: 2.1
Name: pyqtkeybind
Version: 0.0.9
Summary: Global hotkey bindings for Windows and Linux for PyQt apps
Home-page: https://github.com/codito/pyqtkeybind
Author: Arun Mahapatra
Author-email: arun@codito.in
License: MIT
Platform: UNKNOWN
Classifier: License :: OSI Approved :: MIT License
Classifier: Programming Language :: Python
Classifier: Programming Language :: Python :: 3
Classifier: Programming Language :: Python :: 3.6
Classifier: Programming Language :: Python :: Implementation :: CPython
Classifier: Programming Language :: Python :: Implementation :: PyPy
Classifier: Intended Audience :: Developers
Classifier: Development Status :: 3 - Alpha
License-File: LICENSE.md
Requires-Dist: PyQt5
Requires-Dist: xcffib ; sys_platform != "win32"
